skill_monster_scanner/__init__.py
skill_monster_scanner/version.py
skill_monster_scanner/locale/en-us/dialog/monsters.dialog
skill_monster_scanner/locale/en-us/dialog/no_monsters.dialog
skill_monster_scanner/locale/en-us/intents/bed.voc
skill_monster_scanner/locale/en-us/intents/monsters.voc
skill_monster_scanner/locale/en-us/intents/search.voc
skill_monster_scanner/locale/en-us/intents/under.voc
skill_monster_scanner-1.0.1.dist-info/LICENSE
skill_monster_scanner-1.0.1.dist-info/METADATA
skill_monster_scanner-1.0.1.dist-info/WHEEL
skill_monster_scanner-1.0.1.dist-info/entry_points.txt
skill_monster_scanner-1.0.1.dist-info/top_level.txt
skill_monster_scanner-1.0.1.dist-info/RECORD
