Metadata-Version: 2.1
Name: skill-monster-scanner
Version: 1.0.1
Home-page: https://github.com/mikejgray/skill-monster-scanner
Author: Mike Gray
Author-email: mike@graywind.org
License: Apache-2.0
Keywords: ovos skill voice assistant
License-File: LICENSE
Requires-Dist: ovos-utils
Requires-Dist: ovos-bus-client
Requires-Dist: ovos-workshop
Requires-Dist: ovos-plugin-manager
Provides-Extra: test
Requires-Dist: neon-minerva ~=0.2.0 ; extra == 'test'
Requires-Dist: ovos-plugin-manager ; extra == 'test'
Requires-Dist: pytest ; extra == 'test'
Requires-Dist: pytest-cov ; extra == 'test'
Requires-Dist: setuptools ; extra == 'test'
Requires-Dist: ovos-config ; extra == 'test'
